uart_receiver/03_parsing_srec_file/uart_receiver.v
module uart_receiver
(
    input  clock,
    input  reset_n,
    input  rx,
    output reg [7:0] byte_data,
    output           byte_ready
);

    parameter  clock_frequency        = 50000000;
    parameter  baud_rate              = 115200;
    localparam clock_cycles_in_symbol = clock_frequency / baud_rate;

    // Finding edge for start bit

    reg prev_rx;

    always @(posedge clock or negedge reset_n)
    begin
        if (! reset_n)
            prev_rx <= 1;
        else
            prev_rx <= rx;
    end

    wire start_bit_edge = prev_rx & ! rx;

    // Counter to measure distance between symbols

    reg [31:0] counter;
    reg        load_counter;
    reg [31:0] load_counter_value;

    always @(posedge clock or negedge reset_n)
    begin
        if (! reset_n)
            counter <= 0;
        else if (load_counter)
            counter <= load_counter_value;
        else if (counter != 0)
            counter <= counter - 1;
    end

    wire counter_done = counter == 1;

    // Shift register to accumulate data

    reg       shift;
    reg [7:0] shifted_1;
    assign    byte_ready = shifted_1 [0];

    always @ (posedge clock or negedge reset_n)
    begin
        if (! reset_n)
        begin
            shifted_1 <= 0;
        end
        else if (shift)
        begin
            if (shifted_1 == 0)
                shifted_1 <= 8'b10000000;
            else
                shifted_1 <= shifted_1 >> 1;

            byte_data <= { rx, byte_data [7:1] };
        end
        else if (byte_ready)
        begin
            shifted_1 <= 0;
        end
    end

    reg idle, idle_r;

    always @*
    begin
        idle  = idle_r;
        shift = 0;

        load_counter        = 0;
        load_counter_value  = 0;

        if (idle)
        begin
            if (start_bit_edge)
            begin
                load_counter       = 1;
                load_counter_value = clock_cycles_in_symbol * 3 / 2;
           
                idle = 0;
            end
        end
        else if (counter_done)
        begin
            shift = 1;

            load_counter       = 1;
            load_counter_value = clock_cycles_in_symbol;
        end
        else if (byte_ready)
        begin
            idle = 1;
        end
    end

    always @ (posedge clock or negedge reset_n)
    begin
        if (! reset_n)
            idle_r <= 1;
        else
            idle_r <= idle;
    end

endmodule

uart_receiver/02_displaying_bytes/de0_cv/testbench.v
module testbench;

    reg        clock;
    reg        reset_n;
    reg        rx;
    wire [7:0] byte_data;
    wire       byte_ready;

    uart_receiver uart_receiver
    (
        clock,
        reset_n,
        rx,
        byte_data,
        byte_ready
    );

    defparam uart_receiver.clock_frequency = 500;
    defparam uart_receiver.baud_rate       = 10;

    initial
    begin
        clock = 1;

        forever # 50 clock = ! clock;
    end

    initial
    begin
        repeat (2) @(posedge clock);
        reset_n <= 0;
        repeat (2) @(posedge clock);
        rx      <= 1;
        repeat (2) @(posedge clock);
        reset_n <= 1;
    end

    task symbol (input _rx);
    begin
        rx <= _rx;
        repeat (uart_receiver.clock_cycles_in_symbol) @(posedge clock);
    end
    endtask

    integer i, j;

    initial
    begin
        $dumpvars;

        $monitor
        (
            "clock %b reset_n %b rx %b byte_data %h byte_ready %b",
            clock,
            reset_n,
            rx,
            byte_data,
            byte_ready
        );

        @(posedge reset_n);
        @(posedge clock);
 
        symbol (1);
 
        for (i = 0; i < 10; i = i + 1)
        begin
            symbol (0);

            for (j = 0; j < 8; j = j + 1)
                symbol (~ (j & 1));

            repeat (3) symbol (1);
        end

        $finish;
    end

endmodule

uart_receiver/02_displaying_bytes/de0_cv/sim/dump.vcd
$date
	Sun Aug 09 14:40:43 2015
$end
$version
	ModelSim Version 10.3d
$end
$timescale
	1ps
$end

$scope module testbench $end
$var reg 1 ! clock $end
$var reg 1 " reset_n $end
$var reg 1 # rx $end
$var wire 1 $ byte_data [7] $end
$var wire 1 % byte_data [6] $end
$var wire 1 & byte_data [5] $end
$var wire 1 ' byte_data [4] $end
$var wire 1 ( byte_data [3] $end
$var wire 1 ) byte_data [2] $end
$var wire 1 * byte_data [1] $end
$var wire 1 + byte_data [0] $end
$var wire 1 , byte_ready $end
$var integer 32 - i $end
$var integer 32 . j $end

$scope task symbol $end
$var reg 1 / _rx $end
$upscope $end

$scope module uart_receiver $end
$var parameter 32 0 clock_frequency $end
$var parameter 32 1 baud_rate $end
$var parameter 32 2 clock_cycles_in_symbol $end
$var wire 1 3 clock $end
$var wire 1 4 reset_n $end
$var wire 1 5 rx $end
$var reg 8 6 byte_data [7:0] $end
$var wire 1 , byte_ready $end
$var reg 1 7 prev_rx $end
$var wire 1 8 start_bit_edge $end
$var reg 32 9 counter [31:0] $end
$var reg 1 : load_counter $end
$var reg 32 ; load_counter_value [31:0] $end
$var wire 1 < counter_done $end
$var reg 1 = shift $end
$var reg 8 > shifted_1 [7:0] $end
$var reg 1 ? idle $end
$var reg 1 @ idle_r $end
$upscope $end
$upscope $end
$enddefinitions $end
#0
$dumpvars
1!
x"
x#
bx 6
x7
bx 9
x:
bx ;
x=
bx >
x?
x@
x/
b111110100 0
b1010 1
b110010 2
bx -
bx .
x+
x*
x)
x(
x'
x&
x%
x$
x,
x8
x<
x5
x4
13
$end
#50
0!
03
#100
1!
13
#150
0!
03
#200
1!
13
0"
04
17
b0 9
b0 >
1@
0<
0,
1?
0=
0:
b0 ;
#250
0!
03
#300
1!
13
#350
0!
03
#400
1!
13
1#
15
08
#450
0!
03
#500
1!
13
#550
0!
03
#600
1!
13
1"
14
#650
0!
03
#700
1!
13
1/
#750
0!
03
#800
1!
13
#850
0!
03
#900
1!
13
#950
0!
03
#1000
1!
13
#1050
0!
03
#1100
1!
13
#1150
0!
03
#1200
1!
13
#1250
0!
03
#1300
1!
13
#1350
0!
03
#1400
1!
13
#1450
0!
03
#1500
1!
13
#1550
0!
03
#1600
1!
13
#1650
0!
03
#1700
1!
13
#1750
0!
03
#1800
1!
13
#1850
0!
03
#1900
1!
13
#1950
0!
03
#2000
1!
13
#2050
0!
03
#2100
1!
13
#2150
0!
03
#2200
1!
13
#2250
0!
03
#2300
1!
13
#2350
0!
03
#2400
1!
13
#2450
0!
03
#2500
1!
13
#2550
0!
03
#2600
1!
13
#2650
0!
03
#2700
1!
13
#2750
0!
03
#2800
1!
13
#2850
0!
03
#2900
1!
13
#2950
0!
03
#3000
1!
13
#3050
0!
03
#3100
1!
13
#3150
0!
03
#3200
1!
13
#3250
0!
03
#3300
1!
13
#3350
0!
03
#3400
1!
13
#3450
0!
03
#3500
1!
13
#3550
0!
03
#3600
1!
13
#3650
0!
03
#3700
1!
13
#3750
0!
03
#3800
1!
13
#3850
0!
03
#3900
1!
13
#3950
0!
03
#4000
1!
13
#4050
0!
03
#4100
1!
13
#4150
0!
03
#4200
1!
13
#4250
0!
03
#4300
1!
13
#4350
0!
03
#4400
1!
13
#4450
0!
03
#4500
1!
13
#4550
0!
03
#4600
1!
13
#4650
0!
03
#4700
1!
13
#4750
0!
03
#4800
1!
13
#4850
0!
03
#4900
1!
13
#4950
0!
03
#5000
1!
13
#5050
0!
03
#5100
1!
13
#5150
0!
03
#5200
1!
13
#5250
0!
03
#5300
1!
13
#5350
0!
03
#5400
1!
13
#5450
0!
03
#5500
1!
13
#5550
0!
03
#5600
1!
13
#5650
0!
03
#5700
1!
13
b0 -
0/
0#
05
18
1:
b1001011 ;
0?
#5750
0!
03
#5800
1!
13
07
b1001011 9
0@
08
0:
b0 ;
#5850
0!
03
#5900
1!
13
b1001010 9
#5950
0!
03
#6000
1!
13
b1001001 9
#6050
0!
03
#6100
1!
13
b1001000 9
#6150
0!
03
#6200
1!
13
b1000111 9
#6250
0!
03
#6300
1!
13
b1000110 9
#6350
0!
03
#6400
1!
13
b1000101 9
#6450
0!
03
#6500
1!
13
b1000100 9
#6550
0!
03
#6600
1!
13
b1000011 9
#6650
0!
03
#6700
1!
13
b1000010 9
#6750
0!
03
#6800
1!
13
b1000001 9
#6850
0!
03
#6900
1!
13
b1000000 9
#6950
0!
03
#7000
1!
13
b111111 9
#7050
0!
03
#7100
1!
13
b111110 9
#7150
0!
03
#7200
1!
13
b111101 9
#7250
0!
03
#7300
1!
13
b111100 9
#7350
0!
03
#7400
1!
13
b111011 9
#7450
0!
03
#7500
1!
13
b111010 9
#7550
0!
03
#7600
1!
13
b111001 9
#7650
0!
03
#7700
1!
13
b111000 9
#7750
0!
03
#7800
1!
13
b110111 9
#7850
0!
03
#7900
1!
13
b110110 9
#7950
0!
03
#8000
1!
13
b110101 9
#8050
0!
03
#8100
1!
13
b110100 9
#8150
0!
03
#8200
1!
13
b110011 9
#8250
0!
03
#8300
1!
13
b110010 9
#8350
0!
03
#8400
1!
13
b110001 9
#8450
0!
03
#8500
1!
13
b110000 9
#8550
0!
03
#8600
1!
13
b101111 9
#8650
0!
03
#8700
1!
13
b101110 9
#8750
0!
03
#8800
1!
13
b101101 9
#8850
0!
03
#8900
1!
13
b101100 9
#8950
0!
03
#9000
1!
13
b101011 9
#9050
0!
03
#9100
1!
13
b101010 9
#9150
0!
03
#9200
1!
13
b101001 9
#9250
0!
03
#9300
1!
13
b101000 9
#9350
0!
03
#9400
1!
13
b100111 9
#9450
0!
03
#9500
1!
13
b100110 9
#9550
0!
03
#9600
1!
13
b100101 9
#9650
0!
03
#9700
1!
13
b100100 9
#9750
0!
03
#9800
1!
13
b100011 9
#9850
0!
03
#9900
1!
13
b100010 9
#9950
0!
03
#10000
1!
13
b100001 9
#10050
0!
03
#10100
1!
13
b100000 9
#10150
0!
03
#10200
1!
13
b11111 9
#10250
0!
03
#10300
1!
13
b11110 9
#10350
0!
03
#10400
1!
13
b11101 9
#10450
0!
03
#10500
1!
13
b11100 9
#10550
0!
03
#10600
1!
13
b11011 9
#10650
0!
03
#10700
1!
13
b0 .
1/
b11010 9
1#
15
#10750
0!
03
#10800
1!
13
17
b11001 9
#10850
0!
03
#10900
1!
13
b11000 9
#10950
0!
03
#11000
1!
13
b10111 9
#11050
0!
03
#11100
1!
13
b10110 9
#11150
0!
03
#11200
1!
13
b10101 9
#11250
0!
03
#11300
1!
13
b10100 9
#11350
0!
03
#11400
1!
13
b10011 9
#11450
0!
03
#11500
1!
13
b10010 9
#11550
0!
03
#11600
1!
13
b10001 9
#11650
0!
03
#11700
1!
13
b10000 9
#11750
0!
03
#11800
1!
13
b1111 9
#11850
0!
03
#11900
1!
13
b1110 9
#11950
0!
03
#12000
1!
13
b1101 9
#12050
0!
03
#12100
1!
13
b1100 9
#12150
0!
03
#12200
1!
13
b1011 9
#12250
0!
03
#12300
1!
13
b1010 9
#12350
0!
03
#12400
1!
13
b1001 9
#12450
0!
03
#12500
1!
13
b1000 9
#12550
0!
03
#12600
1!
13
b111 9
#12650
0!
03
#12700
1!
13
b110 9
#12750
0!
03
#12800
1!
13
b101 9
#12850
0!
03
#12900
1!
13
b100 9
#12950
0!
03
#13000
1!
13
b11 9
#13050
0!
03
#13100
1!
13
b10 9
#13150
0!
03
#13200
1!
13
b1 9
1<
1=
1:
b110010 ;
#13250
0!
03
#13300
1!
13
b110010 9
b1 >
bx1 6
1+
0<
0=
0:
b0 ;
#13350
0!
03
#13400
1!
13
b110001 9
#13450
0!
03
#13500
1!
13
b110000 9
#13550
0!
03
#13600
1!
13
b101111 9
#13650
0!
03
#13700
1!
13
b101110 9
#13750
0!
03
#13800
1!
13
b101101 9
#13850
0!
03
#13900
1!
13
b101100 9
#13950
0!
03
#14000
1!
13
b101011 9
#14050
0!
03
#14100
1!
13
b101010 9
#14150
0!
03
#14200
1!
13
b101001 9
#14250
0!
03
#14300
1!
13
b101000 9
#14350
0!
03
#14400
1!
13
b100111 9
#14450
0!
03
#14500
1!
13
b100110 9
#14550
0!
03
#14600
1!
13
b100101 9
#14650
0!
03
#14700
1!
13
b100100 9
#14750
0!
03
#14800
1!
13
b100011 9
#14850
0!
03
#14900
1!
13
b100010 9
#14950
0!
03
#15000
1!
13
b100001 9
#15050
0!
03
#15100
1!
13
b100000 9
#15150
0!
03
#15200
1!
13
b11111 9
#15250
0!
03
#15300
1!
13
b11110 9
#15350
0!
03
#15400
1!
13
b11101 9
#15450
0!
03
#15500
1!
13
b11100 9
#15550
0!
03
#15600
1!
13
b11011 9
#15650
0!
03
#15700
1!
13
b1 .
0/
b11010 9
0#
05
18
#15750
0!
03
#15800
1!
13
07
b11001 9
08
#15850
0!
03
#15900
1!
13
b11000 9
#15950
0!
03
#16000
1!
13
b10111 9
#16050
0!
03
#16100
1!
13
b10110 9
#16150
0!
03
#16200
1!
13
b10101 9
#16250
0!
03
#16300
1!
13
b10100 9
#16350
0!
03
#16400
1!
13
b10011 9
#16450
0!
03
#16500
1!
13
b10010 9
#16550
0!
03
#16600
1!
13
b10001 9
#16650
0!
03
#16700
1!
13
b10000 9
#16750
0!
03
#16800
1!
13
b1111 9
#16850
0!
03
#16900
1!
13
b1110 9
#16950
0!
03
#17000
1!
13
b1101 9
#17050
0!
03
#17100
1!
13
b1100 9
#17150
0!
03
#17200
1!
13
b1011 9
#17250
0!
03
#17300
1!
13
b1010 9
#17350
0!
03
#17400
1!
13
b1001 9
#17450
0!
03
#17500
1!
13
b1000 9
#17550
0!
03
#17600
1!
13
b111 9
#17650
0!
03
#17700
1!
13
b110 9
#17750
0!
03
#17800
1!
13
b101 9
#17850
0!
03
#17900
1!
13
b100 9
#17950
0!
03
#18000
1!
13
b11 9
#18050
0!
03
#18100
1!
13
b10 9
#18150
0!
03
#18200
1!
13
b1 9
1<
1=
1:
b110010 ;
#18250
0!
03
#18300
1!
13
b110010 9
b10 >
bx10 6
0+
1*
0<
0=
0:
b0 ;
#18350
0!
03
#18400
1!
13
b110001 9
#18450
0!
03
#18500
1!
13
b110000 9
#18550
0!
03
#18600
1!
13
b101111 9
#18650
0!
03
#18700
1!
13
b101110 9
#18750
0!
03
#18800
1!
13
b101101 9
#18850
0!
03
#18900
1!
13
b101100 9
#18950
0!
03
#19000
1!
13
b101011 9
#19050
0!
03
#19100
1!
13
b101010 9
#19150
0!
03
#19200
1!
13
b101001 9
#19250
0!
03
#19300
1!
13
b101000 9
#19350
0!
03
#19400
1!
13
b100111 9
#19450
0!
03
#19500
1!
13
b100110 9
#19550
0!
03
#19600
1!
13
b100101 9
#19650
0!
03
#19700
1!
13
b100100 9
#19750
0!
03
#19800
1!
13
b100011 9
#19850
0!
03
#19900
1!
13
b100010 9
#19950
0!
03
#20000
1!
13
b100001 9
#20050
0!
03
#20100
1!
13
b100000 9
#20150
0!
03
#20200
1!
13
b11111 9
#20250
0!
03
#20300
1!
13
b11110 9
#20350
0!
03
#20400
1!
13
b11101 9
#20450
0!
03
#20500
1!
13
b11100 9
#20550
0!
03
#20600
1!
13
b11011 9
#20650
0!
03
#20700
1!
13
b10 .
1/
b11010 9
1#
15
#20750
0!
03
#20800
1!
13
17
b11001 9
#20850
0!
03
#20900
1!
13
b11000 9
#20950
0!
03
#21000
1!
13
b10111 9
#21050
0!
03
#21100
1!
13
b10110 9
#21150
0!
03
#21200
1!
13
b10101 9
#21250
0!
03
#21300
1!
13
b10100 9
#21350
0!
03
#21400
1!
13
b10011 9
#21450
0!
03
#21500
1!
13
b10010 9
#21550
0!
03
#21600
1!
13
b10001 9
#21650
0!
03
#21700
1!
13
b10000 9
#21750
0!
03
#21800
1!
13
b1111 9
#21850
0!
03
#21900
1!
13
b1110 9
#21950
0!
03
#22000
1!
13
b1101 9
#22050
0!
03
#22100
1!
13
b1100 9
#22150
0!
03
#22200
1!
13
b1011 9
#22250
0!
03
#22300
1!
13
b1010 9
#22350
0!
03
#22400
1!
13
b1001 9
#22450
0!
03
#22500
1!
13
b1000 9
#22550
0!
03
#22600
1!
13
b111 9
#22650
0!
03
#22700
1!
13
b110 9
#22750
0!
03
#22800
1!
13
b101 9
#22850
0!
03
#22900
1!
13
b100 9
#22950
0!
03
#23000
1!
13
b11 9
#23050
0!
03
#23100
1!
13
b10 9
#23150
0!
03
#23200
1!
13
b1 9
1<
1=
1:
b110010 ;
#23250
0!
03
#23300
1!
13
b110010 9
b100 >
bx101 6
1+
0*
1)
0<
0=
0:
b0 ;
#23350
0!
03
#23400
1!
13
b110001 9
#23450
0!
03
#23500
1!
13
b110000 9
#23550
0!
03
#23600
1!
13
b101111 9
#23650
0!
03
#23700
1!
13
b101110 9
#23750
0!
03
#23800
1!
13
b101101 9
#23850
0!
03
#23900
1!
13
b101100 9
#23950
0!
03
#24000
1!
13
b101011 9
#24050
0!
03
#24100
1!
13
b101010 9
#24150
0!
03
#24200
1!
13
b101001 9
#24250
0!
03
#24300
1!
13
b101000 9
#24350
0!
03
#24400
1!
13
b100111 9
#24450
0!
03
#24500
1!
13
b100110 9
#24550
0!
03
#24600
1!
13
b100101 9
#24650
0!
03
#24700
1!
13
b100100 9
#24750
0!
03
#24800
1!
13
b100011 9
#24850
0!
03
#24900
1!
13
b100010 9
#24950
0!
03
#25000
1!
13
b100001 9
#25050
0!
03
#25100
1!
13
b100000 9
#25150
0!
03
#25200
1!
13
b11111 9
#25250
0!
03
#25300
1!
13
b11110 9
#25350
0!
03
#25400
1!
13
b11101 9
#25450
0!
03
#25500
1!
13
b11100 9
#25550
0!
03
#25600
1!
13
b11011 9
#25650
0!
03
#25700
1!
13
b11 .
0/
b11010 9
0#
05
18
#25750
0!
03
#25800
1!
13
07
b11001 9
08
#25850
0!
03
#25900
1!
13
b11000 9
#25950
0!
03
#26000
1!
13
b10111 9
#26050
0!
03
#26100
1!
13
b10110 9
#26150
0!
03
#26200
1!
13
b10101 9
#26250
0!
03
#26300
1!
13
b10100 9
#26350
0!
03
#26400
1!
13
b10011 9
#26450
0!
03
#26500
1!
13
b10010 9
#26550
0!
03
#26600
1!
13
b10001 9
#26650
0!
03
#26700
1!
13
b10000 9
#26750
0!
03
#26800
1!
13
b1111 9
#26850
0!
03
#26900
1!
13
b1110 9
#26950
0!
03
#27000
1!
13
b1101 9
#27050
0!
03
#27100
1!
13
b1100 9
#27150
0!
03
#27200
1!
13
b1011 9
#27250
0!
03
#27300
1!
13
b1010 9
#27350
0!
03
#27400
1!
13
b1001 9
#27450
0!
03
#27500
1!
13
b1000 9
#27550
0!
03
#27600
1!
13
b111 9
#27650
0!
03
#27700
1!
13
b110 9
#27750
0!
03
#27800
1!
13
b101 9
#27850
0!
03
#27900
1!
13
b100 9
#27950
0!
03
#28000
1!
13
b11 9
#28050
0!
03
#28100
1!
13
b10 9
#28150
0!
03
#28200
1!
13
b1 9
1<
1=
1:
b110010 ;
#28250
0!
03
#28300
1!
13
b110010 9
b1000 >
bx1010 6
0+
1*
0)
1(
0<
0=
0:
b0 ;
#28350
0!
03
#28400
1!
13
b110001 9
#28450
0!
03
#28500
1!
13
b110000 9
#28550
0!
03
#28600
1!
13
b101111 9
#28650
0!
03
#28700
1!
13
b101110 9
#28750
0!
03
#28800
1!
13
b101101 9
#28850
0!
03
#28900
1!
13
b101100 9
#28950
0!
03
#29000
1!
13
b101011 9
#29050
0!
03
#29100
1!
13
b101010 9
#29150
0!
03
#29200
1!
13
b101001 9
#29250
0!
03
#29300
1!
13
b101000 9
#29350
0!
03
#29400
1!
13
b100111 9
#29450
0!
03
#29500
1!
13
b100110 9
#29550
0!
03
#29600
1!
13
b100101 9
#29650
0!
03
#29700
1!
13
b100100 9
#29750
0!
03
#29800
1!
13
b100011 9
#29850
0!
03
#29900
1!
13
b100010 9
#29950
0!
03
#30000
1!
13
b100001 9
#30050
0!
03
#30100
1!
13
b100000 9
#30150
0!
03
#30200
1!
13
b11111 9
#30250
0!
03
#30300
1!
13
b11110 9
#30350
0!
03
#30400
1!
13
b11101 9
#30450
0!
03
#30500
1!
13
b11100 9
#30550
0!
03
#30600
1!
13
b11011 9
#30650
0!
03
#30700
1!
13
b100 .
1/
b11010 9
1#
15
#30750
0!
03
#30800
1!
13
17
b11001 9
#30850
0!
03
#30900
1!
13
b11000 9
#30950
0!
03
#31000
1!
13
b10111 9
#31050
0!
03
#31100
1!
13
b10110 9
#31150
0!
03
#31200
1!
13
b10101 9
#31250
0!
03
#31300
1!
13
b10100 9
#31350
0!
03
#31400
1!
13
b10011 9
#31450
0!
03
#31500
1!
13
b10010 9
#31550
0!
03
#31600
1!
13
b10001 9
#31650
0!
03
#31700
1!
13
b10000 9
#31750
0!
03
#31800
1!
13
b1111 9
#31850
0!
03
#31900
1!
13
b1110 9
#31950
0!
03
#32000
1!
13
b1101 9
#32050
0!
03
#32100
1!
13
b1100 9
#32150
0!
03
#32200
1!
13
b1011 9
#32250
0!
03
#32300
1!
13
b1010 9
#32350
0!
03
#32400
1!
13
b1001 9
#32450
0!
03
#32500
1!
13
b1000 9
#32550
0!
03
#32600
1!
13
b111 9
#32650
0!
03
#32700
1!
13
b110 9
#32750
0!
03
#32800
1!
13
b101 9
#32850
0!
03
#32900
1!
13
b100 9
#32950
0!
03
#33000
1!
13
b11 9
#33050
0!
03
#33100
1!
13
b10 9
#33150
0!
03
#33200
1!
13
b1 9
1<
1=
1:
b110010 ;
#33250
0!
03
#33300
1!
13
b110010 9
b10000 >
bx10101 6
1+
0*
1)
0(
1'
0<
0=
0:
b0 ;
#33350
0!
03
#33400
1!
13
b110001 9
#33450
0!
03
#33500
1!
13
b110000 9
#33550
0!
03
#33600
1!
13
b101111 9
#33650
0!
03
#33700
1!
13
b101110 9
#33750
0!
03
#33800
1!
13
b101101 9
#33850
0!
03
#33900
1!
13
b101100 9
#33950
0!
03
#34000
1!
13
b101011 9
#34050
0!
03
#34100
1!
13
b101010 9
#34150
0!
03
#34200
1!
13
b101001 9
#34250
0!
03
#34300
1!
13
b101000 9
#34350
0!
03
#34400
1!
13
b100111 9
#34450
0!
03
#34500
1!
13
b100110 9
#34550
0!
03
#34600
1!
13
b100101 9
#34650
0!
03
#34700
1!
13
b100100 9
#34750
0!
03
#34800
1!
13
b100011 9
#34850
0!
03
#34900
1!
13
b100010 9
#34950
0!
03
#35000
1!
13
b100001 9
#35050
0!
03
#35100
1!
13
b100000 9
#35150
0!
03
#35200
1!
13
b11111 9
#35250
0!
03
#35300
1!
13
b11110 9
#35350
0!
03
#35400
1!
13
b11101 9
#35450
0!
03
#35500
1!
13
b11100 9
#35550
0!
03
#35600
1!
13
b11011 9
#35650
0!
03
#35700
1!
13
b101 .
0/
b11010 9
0#
05
18
#35750
0!
03
#35800
1!
13
07
b11001 9
08
#35850
0!
03
#35900
1!
13
b11000 9
#35950
0!
03
#36000
1!
13
b10111 9
#36050
0!
03
#36100
1!
13
b10110 9
#36150
0!
03
#36200
1!
13
b10101 9
#36250
0!
03
#36300
1!
13
b10100 9
#36350
0!
03
#36400
1!
13
b10011 9
#36450
0!
03
#36500
1!
13
b10010 9
#36550
0!
03
#36600
1!
13
b10001 9
#36650
0!
03
#36700
1!
13
b10000 9
#36750
0!
03
#36800
1!
13
b1111 9
#36850
0!
03
#36900
1!
13
b1110 9
#36950
0!
03
#37000
1!
13
b1101 9
#37050
0!
03
#37100
1!
13
b1100 9
#37150
0!
03
#37200
1!
13
b1011 9
#37250
0!
03
#37300
1!
13
b1010 9
#37350
0!
03
#37400
1!
13
b1001 9
#37450
0!
03
#37500
1!
13
b1000 9
#37550
0!
03
#37600
1!
13
b111 9
#37650
0!
03
#37700
1!
13
b110 9
#37750
0!
03
#37800
1!
13
b101 9
#37850
0!
03
#37900
1!
13
b100 9
#37950
0!
03
#38000
1!
13
b11 9
#38050
0!
03
#38100
1!
13
b10 9
#38150
0!
03
#38200
1!
13
b1 9
1<
1=
1:
b110010 ;
#38250
0!
03
#38300
1!
13
b110010 9
b100000 >
bx101010 6
0+
1*
0)
1(
0'
1&
0<
0=
0:
b0 ;
#38350
0!
03
#38400
1!
13
b110001 9
#38450
0!
03
#38500
1!
13
b110000 9
#38550
0!
03
#38600
1!
13
b101111 9
#38650
0!
03
#38700
1!
13
b101110 9
#38750
0!
03
#38800
1!
13
b101101 9
#38850
0!
03
#38900
1!
13
b101100 9
#38950
0!
03
#39000
1!
13
b101011 9
#39050
0!
03
#39100
1!
13
b101010 9
#39150
0!
03
#39200
1!
13
b101001 9
#39250
0!
03
#39300
1!
13
b101000 9
#39350
0!
03
#39400
1!
13
b100111 9
#39450
0!
03
#39500
1!
13
b100110 9
#39550
0!
03
#39600
1!
13
b100101 9
#39650
0!
03
#39700
1!
13
b100100 9
#39750
0!
03
#39800
1!
13
b100011 9
#39850
0!
03
#39900
1!
13
b100010 9
#39950
0!
03
#40000
1!
13
b100001 9
#40050
0!
03
#40100
1!
13
b100000 9
#40150
0!
03
#40200
1!
13
b11111 9
#40250
0!
03
#40300
1!
13
b11110 9
#40350
0!
03
#40400
1!
13
b11101 9
#40450
0!
03
#40500
1!
13
b11100 9
#40550
0!
03
#40600
1!
13
b11011 9
#40650
0!
03
#40700
1!
13
b110 .
1/
b11010 9
1#
15
#40750
0!
03
#40800
1!
13
17
b11001 9
#40850
0!
03
#40900
1!
13
b11000 9
#40950
0!
03
#41000
1!
13
b10111 9
#41050
0!
03
#41100
1!
13
b10110 9
#41150
0!
03
#41200
1!
13
b10101 9
#41250
0!
03
#41300
1!
13
b10100 9
#41350
0!
03
#41400
1!
13
b10011 9
#41450
0!
03
#41500
1!
13
b10010 9
#41550
0!
03
#41600
1!
13
b10001 9
#41650
0!
03
#41700
1!
13
b10000 9
#41750
0!
03
#41800
1!
13
b1111 9
#41850
0!
03
#41900
1!
13
b1110 9
#41950
0!
03
#42000
1!
13
b1101 9
#42050
0!
03
#42100
1!
13
b1100 9
#42150
0!
03
#42200
1!
13
b1011 9
#42250
0!
03
#42300
1!
13
b1010 9
#42350
0!
03
#42400
1!
13
b1001 9
#42450
0!
03
#42500
1!
13
b1000 9
#42550
0!
03
#42600
1!
13
b111 9
#42650
0!
03
#42700
1!
13
b110 9
#42750
0!
03
#42800
1!
13
b101 9
#42850
0!
03
#42900
1!
13
b100 9
#42950
0!
03
#43000
1!
13
b11 9
#43050
0!
03
#43100
1!
13
b10 9
#43150
0!
03
#43200
1!
13
b1 9
1<
1=
1:
b110010 ;
#43250
0!
03
#43300
1!
13
b110010 9
b1000000 >
bx1010101 6
1+
0*
1)
0(
1'
0&
1%
0<
0=
0:
b0 ;
#43350
0!
03
#43400
1!
13
b110001 9
#43450
0!
03
#43500
1!
13
b110000 9
#43550
0!
03
#43600
1!
13
b101111 9
#43650
0!
03
#43700
1!
13
b101110 9
#43750
0!
03
#43800
1!
13
b101101 9
#43850
0!
03
#43900
1!
13
b101100 9
#43950
0!
03
#44000
1!
13
b101011 9
#44050
0!
03
#44100
1!
13
b101010 9
#44150
0!
03
#44200
1!
13
b101001 9
#44250
0!
03
#44300
1!
13
b101000 9
#44350
0!
03
#44400
1!
13
b100111 9
#44450
0!
03
#44500
1!
13
b100110 9
#44550
0!
03
#44600
1!
13
b100101 9
#44650
0!
03
#44700
1!
13
b100100 9
#44750
0!
03
#44800
1!
13
b100011 9
#44850
0!
03
#44900
1!
13
b100010 9
#44950
0!
03
#45000
1!
13
b100001 9
#45050
0!
03
#45100
1!
13
b100000 9
#45150
0!
03
#45200
1!
13
b11111 9
#45250
0!
03
#45300
1!
13
b11110 9
#45350
0!
03
#45400
1!
13
b11101 9
#45450
0!
03
#45500
1!
13
b11100 9
#45550
0!
03
#45600
1!
13
b11011 9
#45650
0!
03
#45700
1!
13
b111 .
0/
b11010 9
0#
05
18
#45750
0!
03
#45800
1!
13
07
b11001 9
08
#45850
0!
03
#45900
1!
13
b11000 9
#45950
0!
03
#46000
1!
13
b10111 9
#46050
0!
03
#46100
1!
13
b10110 9
#46150
0!
03
#46200
1!
13
b10101 9
#46250
0!
03
#46300
1!
13
b10100 9
#46350
0!
03
#46400
1!
13
b10011 9
#46450
0!
03
#46500
1!
13
b10010 9
#46550
0!
03
#46600
1!
13
b10001 9
#46650
0!
03
#46700
1!
13
b10000 9
#46750
0!
03
#46800
1!
13
b1111 9
#46850
0!
03
#46900
1!
13
b1110 9
#46950
0!
03
#47000
1!
13
b1101 9
#47050
0!
03
#47100
1!
13
b1100 9
#47150
0!
03
#47200
1!
13
b1011 9
#47250
0!
03
#47300
1!
13
b1010 9
#47350
0!
03
#47400
1!
13
b1001 9
#47450
0!
03
#47500
1!
13
b1000 9
#47550
0!
03
#47600
1!
13
b111 9
#47650
0!
03
#47700
1!
13
b110 9
#47750
0!
03
#47800
1!
13
b101 9
#47850
0!
03
#47900
1!
13
b100 9
#47950
0!
03
#48000
1!
13
b11 9
#48050
0!
03
#48100
1!
13
b10 9
#48150
0!
03
#48200
1!
13
b1 9
1<
1=
1:
b110010 ;
#48250
0!
03
#48300
1!
13
b110010 9
b10000000 >
b10101010 6
0+
1*
0)
1(
0'
1&
0%
1$
0<
1,
0=
0:
b0 ;
1?
#48350
0!
03
#48400
1!
13
b110001 9
b0 >
1@
0,
#48450
0!
03
#48500
1!
13
b110000 9
#48550
0!
03
#48600
1!
13
b101111 9
#48650
0!
03
#48700
1!
13
b101110 9
#48750
0!
03
#48800
1!
13
b101101 9
#48850
0!
03
#48900
1!
13
b101100 9
#48950
0!
03
#49000
1!
13
b101011 9
#49050
0!
03
#49100
1!
13
b101010 9
#49150
0!
03
#49200
1!
13
b101001 9
#49250
0!
03
#49300
1!
13
b101000 9
#49350
0!
03
#49400
1!
13
b100111 9
#49450
0!
03
#49500
1!
13
b100110 9
#49550
0!
03
#49600
1!
13
b100101 9
#49650
0!
03
#49700
1!
13
b100100 9
#49750
0!
03
#49800
1!
13
b100011 9
#49850
0!
03
#49900
1!
13
b100010 9
#49950
0!
03
#50000
1!
13
b100001 9
#50050
0!
03
#50100
1!
13
b100000 9
#50150
0!
03
#50200
1!
13
b11111 9
#50250
0!
03
#50300
1!
13
b11110 9
#50350
0!
03
#50400
1!
13
b11101 9
#50450
0!
03
#50500
1!
13
b11100 9
#50550
0!
03
#50600
1!
13
b11011 9
#50650
0!
03
#50700
1!
13
b1000 .
1/
b11010 9
1#
15
#50750
0!
03
#50800
1!
13
17
b11001 9
#50850
0!
03
#50900
1!
13
b11000 9
#50950
0!
03
#51000
1!
13
b10111 9
#51050
0!
03
#51100
1!
13
b10110 9
